CHANGES.rst
DESCRIPTION.rst
LICENSE
MANIFEST.in
README.md
setup.py
src/adc_faster_whisper/__init__.py
src/adc_faster_whisper/blah.py
src/adc_faster_whisper/class_lister.py
src/adc_faster_whisper/filter/__init__.py
src/adc_faster_whisper/filter/_fw_transcribe.py
src/adc_faster_whisper/tool/__init__.py
src/adc_faster_whisper/tool/srt.py
src/audio_dataset_converter_faster_whisper.egg-info/PKG-INFO
src/audio_dataset_converter_faster_whisper.egg-info/SOURCES.txt
src/audio_dataset_converter_faster_whisper.egg-info/dependency_links.txt
src/audio_dataset_converter_faster_whisper.egg-info/entry_points.txt
src/audio_dataset_converter_faster_whisper.egg-info/requires.txt
src/audio_dataset_converter_faster_whisper.egg-info/top_level.txt